cssaw_central/Session.py
cssaw_central/__init__.py
cssaw_central/csvsql.py
cssaw_central/tests.py
cssaw_central-1.3.0.dist-info/LICENSE.txt
cssaw_central-1.3.0.dist-info/METADATA
cssaw_central-1.3.0.dist-info/WHEEL
cssaw_central-1.3.0.dist-info/entry_points.txt
cssaw_central-1.3.0.dist-info/top_level.txt
cssaw_central-1.3.0.dist-info/RECORD
