Metadata-Version: 2.1
Name: cssaw-central
Version: 1.3.0
Summary: Access Point Module to CSSAW Database
Home-page: https://github.com/CSSAW/CSSAW_Central
Author: Luke Williams
Author-email: williams.luke.2001@gmail.com
License: UNKNOWN
Platform: UNKNOWN
Classifier: Programming Language :: Python :: 3
Classifier: License :: OSI Approved :: Mozilla Public License 2.0 (MPL 2.0)
Classifier: Operating System :: OS Independent
Classifier: Development Status :: 5 - Production/Stable
Requires-Python: >=3.6
Requires-Dist: numpy (>=1.19.0)
Requires-Dist: pandas (>=1.0.5)
Requires-Dist: PyMySQL (>=0.9.3)
Requires-Dist: python-dateutil (>=2.8.1)
Requires-Dist: pytz (>=2020.1)
Requires-Dist: six (>=1.15.0)
Requires-Dist: SQLAlchemy (>=1.3.17)
